tritcask/__init__.py
tritcask/tritcask.py
Tritcask-0.3.dist-info/COPYING
Tritcask-0.3.dist-info/METADATA
Tritcask-0.3.dist-info/WHEEL
Tritcask-0.3.dist-info/top_level.txt
Tritcask-0.3.dist-info/RECORD
