Metadata-Version: 2.1
Name: Tritcask
Version: 0.3
Summary: Append only (type,key)/value store based on bitcask paper.
Home-page: https://github.com/verterok/tritcask
Author: Guillermo Gonzalez
Author-email: guillermo.gonzalez@canonical.com
License: GNU GPL v3
Classifier: Development Status :: 5 - Production/Stable
Classifier: Intended Audience :: Developers
Classifier: License :: OSI Approved :: GNU General Public License (GPL)
Classifier: Operating System :: OS Independent
Classifier: Operating System :: POSIX
Classifier: Programming Language :: Python
Classifier: Topic :: Database
Provides: tritcask
License-File: COPYING
